[
    {"title":"Jamon","description":"Carne de cerdo","price":1000,"code":"C12","stock":30,"category":"Comida"},
    {"title":"Queso","description":"Producto elaborado a base de leche","price":1200,"code":"C20","stock":40,"category":"Comida"},
    {"title":"Salame","description":"Embutido de carne","price":1500,"code":"C15","stock":10,"category":"Comida"},
    {"title":"Pepsi","description":"Bebida gaseosa azucarada","price":800,"code":"B15","stock":10,"category":"Bebida"},
    {"title":"Coca-Cola","description":"Bebida gaseosa azucarada","price":900,"code":"B17","stock":15,"category":"Bebida"},
    {"title":"Papas Lays","description":"Papas fritas saladas embolsadas","price":500,"code":"S3","stock":20,"category":"Snack"},
    {"title":"Pan","description":"Alimento a base de masa de harina","price":800,"code":"C24","stock":20,"category":"Comida"},
    {"title":"Shampo","description":"Se utiliza para la limpieza y cuidado del pelo","price":1100,"code":"H9","stock":50,"category":"Higiene"},
    {"title":"Cepita","description":"Bebida de fruta","price":800,"code":"B25","stock":30,"category":"Bebida"},
    {"title":"Palitos Salados","description":"Palitos crocante salados","price":700,"code":"S11","stock":40,"category":"Snack"},
    {"title":"Yerba Mate","description":"Árbol nativo de la selva paranaense","price":1000,"code":"I1","stock":20,"category":"Infusión"},
    {"title":"Té","description":"Hojas secas molidas o brotes del arbusto Camellia sinensis","price":900,"code":"I3","stock":20,"category":"Infusión"},
    {"title":"Helado","description":"Producido por el congelamiento de una mezcla pasteurizada","price":1200,"code":"P10","stock":32,"category":"Postre"},
    {"title":"Medallon de Carne","description":"Contiene carne picada y otros ingredientes, como soja o almidón","price":1500,"code":"C12","stock":15,"category":"Comida"},
    {"title":"Arroz","description":"Semilla debidamente procesada","price":1500,"code":"C2","stock":15,"category":"Comida"},
    {"title":"Agua Mineral","description":"Agua sin gas proveniente de manantiales naturales","price":600,"code":"B30","stock":25,"category":"Bebida"},
    {"title":"Galletas","description":"Producto horneado a base de harina, azúcar y grasa","price":550,"code":"S8","stock":35,"category":"Snack"},
    {"title":"Pasta Dental","description":"Gel que se utiliza con un cepillo para limpiar los dientes","price":700,"code":"H15","stock":20,"category":"Higiene"},
    {"title":"Gaseosa de Naranja","description":"Bebida refrescante con sabor a naranja","price":850,"code":"B21","stock":18,"category":"Bebida"},
    {"title":"Chocolate","description":"Producto dulce elaborado con cacao","price":1200,"code":"S15","stock":22,"category":"Snack"},
    {"title":"Acondicionador","description":"Producto que se utiliza después del shampoo para suavizar el cabello","price":1000,"code":"H18","stock":28,"category":"Higiene"},
    {"title":"Café","description":"Bebida estimulante preparada a partir de granos de café tostados molidos","price":1100,"code":"I6","stock":15,"category":"Infusión"},
    {"title":"Gel de Ducha","description":"Producto líquido utilizado para limpiar el cuerpo durante la ducha","price":900,"code":"H22","stock":30,"category":"Higiene"},
    {"title":"Nueces","description":"Fruto seco comestible con cáscara dura","price":1300,"code":"S22","stock":12,"category":"Snack"},
    {"title":"Leche","description":"Líquido nutritivo producido por las glándulas mamarias de los mamíferos","price":950,"code":"B35","stock":25,"category":"Bebida"},
    {"title":"Cereal","description":"Producto alimenticio hecho a partir de granos y frutas","price":700,"code":"S18","stock":20,"category":"Snack"},
    {"title":"Desodorante","description":"Producto que se utiliza para prevenir el mal olor corporal","price":800,"code":"H25","stock":40,"category":"Higiene"},
    {"title":"Tortillas","description":"Producto de pan plano hecho de masa de maíz o harina de trigo","price":600,"code":"S25","stock":30,"category":"Snack"},
    {"title":"Crema Hidratante","description":"Producto que se aplica sobre la piel para mantenerla suave e hidratada","price":1200,"code":"H28","stock":20,"category":"Higiene"},
    {"title":"Zumo de Naranja","description":"Bebida hecha a partir del jugo de naranjas","price":850,"code":"B40","stock":15,"category":"Bebida"},
    {"title":"Muffins","description":"Pequeños pasteles individuales","price":1000,"code":"S28","stock":18,"category":"Snack"},
    {"title":"Sopa Instantánea","description":"Sopa preparada rápidamente añadiendo agua caliente","price":500,"code":"C30","stock":25,"category":"Comida"},
    {"title":"Perfume","description":"Fragancia líquida o sólida que se utiliza para dar un buen olor al cuerpo","price":1500,"code":"H35","stock":10,"category":"Higiene"},
    {"title":"Miel","description":"Sustancia dulce producida por las abejas a partir del néctar de las flores","price":1100,"code":"S32","stock":22,"category":"Snack"},
    {"title":"Papas Pringles","description":"Papas fritas en forma de láminas","price":700,"code":"S35","stock":25,"category":"Snack"},
    {"title":"Ensalada Mixta","description":"Mezcla de vegetales frescos","price":900,"code":"C40","stock":15,"category":"Comida"},
    {"title":"Agua con Gas","description":"Agua con burbujas adicionadas artificialmente","price":600,"code":"B45","stock":20,"category":"Bebida"},
    {"title":"Galletas de Avena","description":"Galletas con avena y pasas","price":550,"code":"S38","stock":35,"category":"Snack"},
    {"title":"Cepillo de Dientes","description":"Instrumento utilizado para la higiene bucal","price":300,"code":"H40","stock":50,"category":"Higiene"},
    {"title":"Sushi","description":"Plato japonés con arroz y pescado crudo","price":1200,"code":"C42","stock":18,"category":"Comida"},
    {"title":"Bebida Energética","description":"Bebida diseñada para dar un impulso de energía","price":1000,"code":"B50","stock":15,"category":"Bebida"},
    {"title":"Frutas Secas","description":"Frutas deshidratadas como pasas y ciruelas","price":850,"code":"S42","stock":22,"category":"Snack"},
    {"title":"Gel Antibacterial","description":"Gel que mata bacterias en las manos","price":500,"code":"H45","stock":30,"category":"Higiene"},
    {"title":"Batido de Frutas","description":"Mezcla de frutas batidas con leche o yogurt","price":1100,"code":"B55","stock":20,"category":"Bebida"},
    {"title":"Chocolate Blanco","description":"Chocolate elaborado con manteca de cacao","price":1300,"code":"S48","stock":12,"category":"Snack"},
    {"title":"Desinfectante de Superficies","description":"Producto para desinfectar superficies","price":750,"code":"H50","stock":25,"category":"Higiene"},
    {"title":"Tequila","description":"Bebida alcohólica destilada de la planta de agave","price":2000,"code":"B60","stock":10,"category":"Bebida"},
    {"title":"Pizza Congelada","description":"Pizza lista para hornear desde el congelador","price":1600,"code":"C52","stock":15,"category":"Comida"},
    {"title":"Cereal de Granola","description":"Mezcla de granos, frutas y frutos secos","price":750,"code":"S52","stock":20,"category":"Snack"},
    {"title":"Aftershave","description":"Producto utilizado después del afeitado","price":900,"code":"H55","stock":18,"category":"Higiene"},
    {"title":"Zumo de Manzana","description":"Bebida hecha a partir del jugo de manzanas","price":800,"code":"B65","stock":22,"category":"Bebida"},
    {"title":"Pan Integral","description":"Pan elaborado con harina integral","price":600,"code":"C58","stock":30,"category":"Comida"},
    {"title":"Chicles","description":"Producto para masticar y refrescar el aliento","price":300,"code":"S58","stock":40,"category":"Snack"},
    {"title":"Acondicionador de Barba","description":"Producto para suavizar y acondicionar la barba","price":1200,"code":"H60","stock":15,"category":"Higiene"},
    {"title":"Zumo de Uva","description":"Bebida hecha a partir del jugo de uvas","price":850,"code":"B70","stock":18,"category":"Bebida"},
    {"title":"Almendras","description":"Fruto seco con cáscara dura","price":1300,"code":"S62","stock":12,"category":"Snack"},
    {"title":"Cepillo de Pelo","description":"Instrumento utilizado para peinar el cabello","price":400,"code":"H65","stock":25,"category":"Higiene"},
    {"title":"Sopa en Lata","description":"Sopa enlatada lista para calentar y servir","price":550,"code":"C62","stock":20,"category":"Comida"},
    {"title":"Perfume Floral","description":"Fragancia con notas florales","price":1400,"code":"H68","stock":20,"category":"Higiene"},
    {"title":"Palomitas de Maíz","description":"Maíz inflado y salado","price":400,"code":"S68","stock":25,"category":"Snack"}
]